kanagata/__init__.py
kanagata/builder.py
kanagata/repository.py
kanagata/restriction.py
kanagata/structure.py
kanagata-0.0.1.dist-info/DESCRIPTION.rst
kanagata-0.0.1.dist-info/entry_points.txt
kanagata-0.0.1.dist-info/METADATA
kanagata-0.0.1.dist-info/metadata.json
kanagata-0.0.1.dist-info/RECORD
kanagata-0.0.1.dist-info/top_level.txt
kanagata-0.0.1.dist-info/WHEEL
