Metadata-Version: 2.0
Name: kanagata
Version: 0.0.1
Summary: restricted dict
Home-page: https://github.com/podhmo/kanagata
Author: podhmo
Author-email: ababjam61+github@gmail.com
License: UNKNOWN
Keywords: restricted dict,dict
Platform: UNKNOWN
Classifier: Programming Language :: Python
Classifier: Programming Language :: Python :: Implementation :: CPython
Provides-Extra: docs
Provides-Extra: testing
